LICENSE
MANIFEST.in
README.md
setup.py
web_cache/__init__.py
web_cache.egg-info/PKG-INFO
web_cache.egg-info/SOURCES.txt
web_cache.egg-info/dependency_links.txt
web_cache.egg-info/top_level.txt