Metadata-Version: 2.1
Name: web-cache
Version: 1.1.0
Summary: Simple persistent cache storage, with different cache eviction strategies, and optional compression
Home-page: https://github.com/desbma/web_cache
Author: desbma
License: UNKNOWN
Download-URL: https://github.com/desbma/web_cache/archive/1.1.0.tar.gz
Keywords: cache,sqlite3,key-value,persistent
Platform: UNKNOWN
Classifier: Development Status :: 5 - Production/Stable
Classifier: Intended Audience :: Developers
Classifier: License :: OSI Approved :: GNU Lesser General Public License v2 or later (LGPLv2+)
Classifier: Operating System :: OS Independent
Classifier: Programming Language :: Python
Classifier: Programming Language :: Python :: 3
Classifier: Programming Language :: Python :: 3 :: Only
Classifier: Programming Language :: Python :: 3.4
Classifier: Programming Language :: Python :: 3.5
Classifier: Programming Language :: Python :: 3.6
Classifier: Topic :: Database
Classifier: Topic :: Software Development :: Libraries :: Python Modules
